Compiled from "Test.java"
public class com.hns.learn.model.Test {
  public static int orderNum;

  public com.hns.learn.model.Test();
    Code:
       0: aload_0
       1: invokespecial #1                  // Method java/lang/Object."<init>":()V
       4: return

  public java.lang.String getName();
    Code:
       0: aload_0
       1: getfield      #2                  // Field name:Ljava/lang/String;
       4: areturn

  public void setName(java.lang.String);
    Code:
       0: aload_0
       1: aload_1
       2: putfield      #2                  // Field name:Ljava/lang/String;
       5: return

  public static void main(java.lang.String[]);
    Code:
       0: new           #11                 // class com/hns/learn/model/Test
       3: dup
       4: invokespecial #12                 // Method "<init>":()V
       7: ldc           #13                 // String hello world!
       9: invokespecial #14                 // Method print:(Ljava/lang/String;)Ljava/lang/String;
      12: pop
      13: return

  static {};
    Code:
       0: iconst_1
       1: putstatic     #15                 // Field orderNum:I
       4: return
}
